qtile_profiles.py
qtile_profiles-0.1.2.dist-info/LICENSE
qtile_profiles-0.1.2.dist-info/WHEEL
qtile_profiles-0.1.2.dist-info/METADATA
qtile_profiles-0.1.2.dist-info/RECORD
