Metadata-Version: 2.1
Name: qtile-profiles
Version: 0.1.2
Summary: A profile manger for qtile
Author-email: Paul Hoffmann <phfn@phfn.de>
Classifier: License :: OSI Approved :: GNU General Public License v3 or later (GPLv3+)
Project-URL: Home, https://phfn.de
Project-URL: Source, https://github.com/phfn/qtile-profiles
